orlike/__init__.py
orlike/__version__.py
orlike/index.py
orlike/templates/orlike.html
orlike/templates/test.html
orlike-0.1.38.dist-info/LICENSE
orlike-0.1.38.dist-info/METADATA
orlike-0.1.38.dist-info/WHEEL
orlike-0.1.38.dist-info/top_level.txt
orlike-0.1.38.dist-info/RECORD
