Metadata-Version: 2.1
Name: orlike
Version: 0.1.38
Summary: A blog like plugin
Home-page: https://github.com/caibingcheng/orlike
Author: caibingcheng
Author-email: jack_cbc@163.com
License: UNKNOWN
Project-URL: Bug Reports, https://github.com/caibingcheng/orlike/issues
Project-URL: Source, https://github.com/caibingcheng/orlike
Keywords: plugin,orlike,blog
Platform: UNKNOWN
Classifier: Development Status :: 3 - Alpha
Classifier: Intended Audience :: Developers
Classifier: Topic :: Software Development :: Build Tools
Classifier: License :: OSI Approved :: MIT License
Classifier: Programming Language :: Python :: 3
Classifier: Programming Language :: Python :: 3.6
Classifier: Programming Language :: Python :: 3.7
Classifier: Programming Language :: Python :: 3.8
Classifier: Programming Language :: Python :: 3.9
Classifier: Programming Language :: Python :: 3 :: Only
Requires-Python: >=3.6, <4
License-File: LICENSE
Requires-Dist: Flask (>=1.1.2)
Requires-Dist: leancloud (>=2.9.3)
Requires-Dist: flask-cors
Provides-Extra: dev
Requires-Dist: pytest (==6.2.2) ; extra == 'dev'
Requires-Dist: pytest-cov (==2.11.1) ; extra == 'dev'
Requires-Dist: tox (~=3.21.0) ; extra == 'dev'
